README.md
setup.py
Flask_Secrets.egg-info/PKG-INFO
Flask_Secrets.egg-info/SOURCES.txt
Flask_Secrets.egg-info/dependency_links.txt
Flask_Secrets.egg-info/entry_points.txt
Flask_Secrets.egg-info/not-zip-safe
Flask_Secrets.egg-info/requires.txt
Flask_Secrets.egg-info/top_level.txt
flask_secrets/cli.py