Metadata-Version: 1.2
Name: Flask-Secrets
Version: 0.1.0
Summary: A Flask extension to generate random secret tokens.
Home-page: https://github.com/nickjj/flask-secrets
Author: Nick Janetakis
Author-email: nick.janetakis@gmail.com
License: MIT
Platform: any
Classifier: Environment :: Web Environment
Classifier: Framework :: Flask
Classifier: Intended Audience :: Developers
Classifier: License :: OSI Approved :: MIT License
Classifier: Operating System :: OS Independent
Classifier: Programming Language :: Python
Classifier: Programming Language :: Python :: 3
Classifier: Topic :: Internet :: WWW/HTTP :: Dynamic Content
Classifier: Topic :: Software Development :: Libraries :: Python Modules
Classifier: Topic :: Security :: Cryptography
Requires-Python: >=3.6
